AUTHORS.rst
CONTRIBUTING.rst
HISTORY.rst
LICENSE
MANIFEST.in
README.rst
requirements.txt
setup.cfg
setup.py
djgunicorn/__init__.py
djgunicorn/config.py
djgunicorn/gunicorn.py
djgunicorn/logging.py
djgunicorn.egg-info/PKG-INFO
djgunicorn.egg-info/SOURCES.txt
djgunicorn.egg-info/dependency_links.txt
djgunicorn.egg-info/not-zip-safe
djgunicorn.egg-info/requires.txt
djgunicorn.egg-info/top_level.txt
djgunicorn/management/__init__.py
djgunicorn/management/commands/__init__.py
djgunicorn/management/commands/gunserver.py
djgunicorn/wsgi/__init__.py
djgunicorn/wsgi/base.py
djgunicorn/wsgi/staticfiles.py
requirements/base.txt
requirements/dev.txt
requirements/test.txt