Metadata-Version: 1.1
Name: djgunicorn
Version: 0.3.0
Summary: Run Django development server with Gunicorn.
Home-page: https://github.com/uranusjr/django-gunicorn
Author: Tzu-ping Chung
Author-email: uranusjr@gmail.com
License: BSD
Keywords: django-gunicorn
Platform: UNKNOWN
Classifier: Development Status :: 3 - Alpha
Classifier: Framework :: Django
Classifier: Framework :: Django :: 1.7
Classifier: Framework :: Django :: 1.8
Classifier: Intended Audience :: Developers
Classifier: License :: OSI Approved :: BSD License
Classifier: Natural Language :: English
Classifier: Programming Language :: Python :: 2
Classifier: Programming Language :: Python :: 2.7
Classifier: Programming Language :: Python :: 3
Classifier: Programming Language :: Python :: 3.3
Classifier: Programming Language :: Python :: 3.4
Classifier: Programming Language :: Python :: 3.5
